pypetkitapi/__init__.py
pypetkitapi/bluetooth.py
pypetkitapi/client.py
pypetkitapi/command.py
pypetkitapi/const.py
pypetkitapi/containers.py
pypetkitapi/exceptions.py
pypetkitapi/feeder_container.py
pypetkitapi/litter_container.py
pypetkitapi/media.py
pypetkitapi/purifier_container.py
pypetkitapi/py.typed
pypetkitapi/schedule_container.py
pypetkitapi/utils.py
pypetkitapi/water_fountain_container.py
pypetkitapi-1.22.2.dist-info/METADATA
pypetkitapi-1.22.2.dist-info/WHEEL
pypetkitapi-1.22.2.dist-info/licenses/LICENSE
pypetkitapi-1.22.2.dist-info/RECORD
