Metadata-Version: 2.4
Name: pypetkitapi
Version: 1.22.2
Summary: Python client for PetKit API
License: MIT
License-File: LICENSE
Keywords: petkit,api,client,pet,iot
Author: Jezza34000
Author-email: info@mail.com
Requires-Python: >=3.11
Classifier: Development Status :: 5 - Production/Stable
Classifier: Intended Audience :: Developers
Classifier: License :: OSI Approved :: MIT License
Classifier: Programming Language :: Python :: 3
Classifier: Programming Language :: Python :: 3.11
Classifier: Programming Language :: Python :: 3.12
Classifier: Programming Language :: Python :: 3.13
Classifier: Programming Language :: Python :: 3.14
Classifier: Topic :: Home Automation
Classifier: Topic :: Software Development :: Libraries :: Python Modules
Requires-Dist: aiofiles (>=24.1.0,<25.0.0)
Requires-Dist: aiohttp (>=3.11.11,<4.0.0)
Requires-Dist: m3u8 (>=6.0.0,<7.0.0)
Requires-Dist: pycryptodome (>=3.19.1,<4.0.0)
Requires-Dist: pydantic (>=2.10.4,<3.0.0)
Requires-Dist: tenacity (>=9.1.2,<10.0.0)
Project-URL: Homepage, https://github.com/Jezza34000/pypetkit
Project-URL: Repository, https://github.com/Jezza34000/pypetkit
